Workbook

Sheet Read me
A1: HCLS AI Agent Suite — ROI Calculator
A3: HOW TO USE
A4: 1. Open the 'Assumptions' tab and set the blue input cells to your organization's baseline.
A5: 2. Open each agent tab; set the blue per-agent input cells (volumes, rates, expected reduction).
A6: 3. Read the green 'Modeled annual value' and the 'Summary' tab. Edit only blue cells.
A8: DISCIPLINE (so the model stays board-defensible)
A9: • Every anchor figure traces to ../HCLS-DECK-SOURCES.md with a source-class tag.
A10: • Outcomes are modeled at YOUR baseline — they are not guaranteed and depend on data quality,
A11: process design, and adoption.
A12: • 'Expected reduction %' is a planning assumption the SA sets WITH the customer, not a vendor promise.
A13: • Bedrock inference + infrastructure + SI delivery cost must be modeled separately (see Assumptions).
A15: SOURCE ANCHORS USED
... A22: • MLR: 50–70% time-to-deliver reduction potential — McKinsey.

Sheet Assumptions
A1: Global Assumptions (edit blue cells)
A2: Parameter | B2: Value | C2: Note
A3: Fully-loaded labor cost / FTE / yr | B3: 175000 | C3: Blended loaded rate; adjust per geography/role.
A4: Fully-loaded labor cost / hour | B4: 95 | C4: Used for hours-saved conversions.
A5: Lost/delayed peak sales per day of delay | B5: 800000 | C5: Tufts CSDD 2024 (asset-dependent).
A6: Phase III direct trial cost per day | B6: 55716 | C6: Tufts CSDD 2024.
A7: Direct cost of a substantial Phase III amendment | B7: 535000 | C7: Tufts CSDD 2016.
A8: Estimated Bedrock inference + infra / yr (per agent) | B8: 120000 | C8: Replace with your TCO-model figure.

Sheet Summary
A1: Suite ROI Summary (modeled at your baseline)
A2: # | B2: Agent | C2: Modeled annual value | D2: Net of platform cost
A3: 01 | B3: Regulatory Writing | C3: ='01 Regulatory Writing'!B9 | D3: ='01 Regulatory Writing'!B11
A4: 02 | B4: Pharmacovigilance | C4: ='02 Pharmacovigilance'!B9 | D4: ='02 Pharmacovigilance'!B11
A5: 03 | B5: Clinical Trial Ops & TMF | C5: ='03 Clinical Trial Ops & TMF'!B9 | D5: ='03 Clinical Trial Ops & TMF'!B11
A6: 04 | B6: Site & Patient Matching | C6: ='04 Site & Patient Matching'!B10 | D6: ='04 Site & Patient Matching'!B12
A7: 05 | B7: Quality / CAPA | C7: ='05 Quality - CAPA'!B10 | D7: ='05 Quality - CAPA'!B12
A8: 06 | B8: Protocol Design | C8: ='06 Protocol Design'!B10 | D8: ='06 Protocol Design'!B12
A9: 07 | B9: RWE / HEOR | C9: ='07 RWE - HEOR'!B9 | D9: ='07 RWE - HEOR'!B11
A10: 08 | B10: Medical Affairs / MSL | C10: ='08 Medical Affairs - MSL'!B9 | D10: ='08 Medical Affairs - MSL'!B11
B11: SUITE TOTAL | C11: =SUM(C3:C10) | D11: =SUM(D3:D10)
A13: All figures modeled from the cited anchors in HCLS-DECK-SOURCES.md, applied to your inputs. Not a guarantee. Land-first agents 01/02/03/08 typically anchor the Phase-1 business case.

Sheet 01 Regulatory Writing
A1: Agent 01 — Regulatory Writing (edit blue cells)
A2: Inputs (your baseline)
A3: Submissions / major filings per year | B3: 6
A4: Avg. writer hours per submission (drafting+assembly) | B4: 1200
A5: Expected hours reduction % (Merck-class pilots ~40-55%) | B5: 0.4
A6: Avg. submission delay avoided (days/filing) | B6: 10
A7: Results (modeled)
A8: Cost of doing nothing (delay NPV exposure, modeled) | B8: =B3*B6*Assumptions!$B$5
A9: Modeled annual value of the agent | B9: =(B3*B4*B5*Assumptions!$B$4) + (B3*B6*Assumptions!$B$5)
A10: Less: est. Bedrock inference + infra / yr | B10: =-Assumptions!$B$8
A11: Net modeled annual value | B11: =B9+B10
A13: Modeled at your baseline; not guaranteed. SI delivery cost is separate (see TCO model).

Sheet 02 Pharmacovigilance
A1: Agent 02 — Pharmacovigilance (edit blue cells)
A2: Inputs (your baseline)
A3: ICSR cases processed per year | B3: 100000
A4: Avg. processing minutes per case today | B4: 69
A5: Expected processing-time reduction % (Schmider 40-70%) | B5: 0.4
A6: Blended cost per processing hour | B6: 95
A7: Results (modeled)
A8: Annual case-processing labor today (modeled) | B8: =(B3*B4/60)*B6
A9: Modeled annual value of the agent | B9: =(B3*B4/60)*B5*B6
A10: Less: est. Bedrock inference + infra / yr | B10: =-Assumptions!$B$8
A11: Net modeled annual value | B11: =B9+B10
A13: Modeled at your baseline; not guaranteed. SI delivery cost is separate (see TCO model).

Sheet 03 Clinical Trial Ops & TMF
A1: Agent 03 — Clinical Trial Ops & TMF (edit blue cells)
A2: Inputs (your baseline)
A3: Active pivotal (Phase III) trials | B3: 3
A4: Avg. database-lock / TMF slip avoided (days/trial) | B4: 20
A5: Lost sales per day of delay | B5: 800000
A6: Phase III direct cost per day | B6: 55716
A7: Results (modeled)
A8: Exposure per avoided slip across active trials (modeled) | B8: =B3*B4*(B5+B6)
A9: Modeled annual value of the agent | B9: =B3*B4*(B5+B6)
A10: Less: est. Bedrock inference + infra / yr | B10: =-Assumptions!$B$8
A11: Net modeled annual value | B11: =B9+B10
A13: Modeled at your baseline; not guaranteed. SI delivery cost is separate (see TCO model).

Sheet 04 Site & Patient Matching
A1: Agent 04 — Site & Patient Matching (edit blue cells)
A2: Inputs (your baseline)
A3: New trial launches per year | B3: 4
A4: Enrollment days pulled in per launch | B4: 30
A5: Lost sales per day of delay | B5: 800000
A6: Non-enrolling site activations avoided / yr | B6: 8
A7: Cost per wasted site activation | B7: 40000
A8: Results (modeled)
A9: Accelerated revenue from faster enrollment (modeled) | B9: =B3*B4*B5
A10: Modeled annual value of the agent | B10: =(B3*B4*B5)+(B6*B7)
A11: Less: est. Bedrock inference + infra / yr | B11: =-Assumptions!$B$8
A12: Net modeled annual value | B12: =B10+B11
A14: Modeled at your baseline; not guaranteed. SI delivery cost is separate (see TCO model).

Sheet 05 Quality - CAPA
A1: Agent 05 — Quality / CAPA (edit blue cells)
A2: Inputs (your baseline)
A3: Complaints / quality events per year | B3: 5000
A4: Avg. analyst hours per CAPA / investigation | B4: 12
A5: Expected hours reduction % (triage+RCA draft) | B5: 0.3
A6: Blended cost per hour | B6: 95
A7: Recall-exposure value at risk reduced / yr | B7: 0
A8: Results (modeled)
A9: Annual CAPA / investigation labor today (modeled) | B9: =B3*B4*B6
A10: Modeled annual value of the agent | B10: =(B3*B4*B5*B6)+B7
A11: Less: est. Bedrock inference + infra / yr | B11: =-Assumptions!$B$8
A12: Net modeled annual value | B12: =B10+B11
A14: Modeled at your baseline; not guaranteed. SI delivery cost is separate (see TCO model).

Sheet 06 Protocol Design
A1: Agent 06 — Protocol Design (edit blue cells)
A2: Inputs (your baseline)
A3: Phase III protocols authored per year | B3: 4
A4: Avoidable substantial amendments prevented / protocol | B4: 0.5
A5: Direct cost per Phase III amendment | B5: 535000
A6: Cycle delay avoided per prevented amendment (days) | B6: 70
A7: Lost sales per day of delay | B7: 800000
A8: Results (modeled)
A9: Direct amendment cost avoided (modeled) | B9: =B3*B4*B5
A10: Modeled annual value of the agent | B10: =B3*B4*(B5+(B6*B7))
A11: Less: est. Bedrock inference + infra / yr | B11: =-Assumptions!$B$8
A12: Net modeled annual value | B12: =B10+B11
A14: Modeled at your baseline; not guaranteed. SI delivery cost is separate (see TCO model).

Sheet 07 RWE - HEOR
A1: Agent 07 — RWE / HEOR (edit blue cells)
A2: Inputs (your baseline)
A3: RWE / HEOR analysts (FTE) | B3: 20
A4: Fully-loaded cost per analyst / yr | B4: 150000
A5: Share of time on data prep today (Anaconda ~45%) | B5: 0.45
A6: Share of prep time reclaimed | B6: 0.5
A7: Results (modeled)
A8: Non-analytic labor cost today (modeled) | B8: =B3*B4*B5
A9: Modeled annual value of the agent | B9: =B3*B4*B5*B6
A10: Less: est. Bedrock inference + infra / yr | B10: =-Assumptions!$B$8
A11: Net modeled annual value | B11: =B9+B10
A13: Modeled at your baseline; not guaranteed. SI delivery cost is separate (see TCO model).

Sheet 08 Medical Affairs - MSL
A1: Agent 08 — Medical Affairs / MSL (edit blue cells)
A2: Inputs (your baseline)
A3: MLR-reviewed content items per year | B3: 4000
A4: Avg. reviewer hours per item | B4: 3
A5: Expected time-to-deliver reduction % (McKinsey 50-70%) | B5: 0.5
A6: Blended cost per reviewer hour | B6: 110
A7: Results (modeled)
A8: Annual MLR review labor today (modeled) | B8: =B3*B4*B6
A9: Modeled annual value of the agent | B9: =B3*B4*B5*B6
A10: Less: est. Bedrock inference + infra / yr | B10: =-Assumptions!$B$8
A11: Net modeled annual value | B11: =B9+B10
A13: Modeled at your baseline; not guaranteed. SI delivery cost is separate (see TCO model).
